{
  "publicPath": "/_nuxt/",
  "all": [
    "../server/index.spa.html",
    "../server/index.ssr.html",
    "13c39e1.modern.js",
    "157e5a7.modern.js",
    "1bf87da.modern.js",
    "31d3a40.modern.js",
    "588bc92.modern.js",
    "5b5ff44.modern.js",
    "629f580.modern.js",
    "6ec9b55.modern.js",
    "74e7225.modern.js",
    "90e3a87.modern.js",
    "941945c.modern.js",
    "LICENSES",
    "a15f9a5.modern.js",
    "bec7cb8.modern.js",
    "c15d5f1.modern.js",
    "e694531.modern.js",
    "f6d72cb.modern.js",
    "fdf6858.modern.js"
  ],
  "initial": [
    "31d3a40.modern.js",
    "157e5a7.modern.js",
    "90e3a87.modern.js",
    "588bc92.modern.js"
  ],
  "async": [
    "13c39e1.modern.js",
    "1bf87da.modern.js",
    "5b5ff44.modern.js",
    "629f580.modern.js",
    "6ec9b55.modern.js",
    "74e7225.modern.js",
    "941945c.modern.js",
    "a15f9a5.modern.js",
    "bec7cb8.modern.js",
    "c15d5f1.modern.js",
    "e694531.modern.js",
    "f6d72cb.modern.js",
    "fdf6858.modern.js"
  ],
  "modules": {
    "10734216": [
      3
    ],
    "12640612": [
      3
    ],
    "21511070": [
      3
    ],
    "22672664": [
      6
    ],
    "23671383": [
      11
    ],
    "33317058": [
      6
    ],
    "42820198": [
      3
    ],
    "49306145": [
      11
    ],
    "50828542": [
      3
    ],
    "52531689": [
      11
    ],
    "53488230": [
      11
    ],
    "64016652": [
      3
    ],
    "65143770": [
      11
    ],
    "68779247": [
      11
    ],
    "72045124": [
      4
    ],
    "78308543": [
      3
    ],
    "88547358": [
      11
    ],
    "99078538": [
      3
    ],
    "22a7909a": [
      3
    ],
    "4ef40c3a": [
      11
    ],
    "895bb22c": [
      6
    ],
    "5f65c86d": [
      11
    ],
    "6f5cef29": [
      3
    ],
    "2e99ec68": [
      3
    ],
    "28be3f8a": [
      3
    ],
    "f5d5938e": [
      11
    ],
    "435b7796": [
      11
    ],
    "3baceab8": [
      11
    ],
    "4bc23c19": [
      11
    ],
    "9ab63426": [
      3
    ],
    "73f2e97a": [
      3
    ],
    "25caaaf5": [
      11
    ],
    "c4cd8d6a": [
      3
    ],
    "be513786": [
      3
    ],
    "969adf88": [
      3
    ],
    "31cf00c2": [
      3
    ],
    "1509e80a": [
      3
    ],
    "5badb25b": [
      3
    ],
    "a4edf20e": [
      3
    ],
    "53ad1266": [
      3
    ],
    "510be875": [
      3
    ],
    "e95a9c8c": [
      3
    ],
    "377d6b7e": [
      3
    ],
    "0aafc4c2": [
      3
    ],
    "b8121298": [
      11
    ],
    "23a8420a": [
      11
    ],
    "b613df4a": [
      11
    ],
    "4c8db60c": [
      11
    ],
    "9911454c": [
      3
    ],
    "0d1d285c": [
      3
    ],
    "50fdf1fa": [
      3
    ],
    "01bf6190": [
      3
    ],
    "31b5a24b": [
      3
    ],
    "17d463e0": [
      3
    ],
    "4e436e68": [
      3
    ],
    "06aa0cb7": [
      3
    ],
    "07c30312": [
      11
    ],
    "d313e1ae": [
      6
    ],
    "7289d34a": [
      6
    ],
    "07c1b03a": [
      6
    ],
    "b8ce65ee": [
      6
    ],
    "0538df92": [
      6
    ],
    "dca816cc": [
      6
    ],
    "13c9de8c": [
      6
    ],
    "6a7c21e2": [
      6
    ],
    "717dd905": [
      6
    ],
    "86a7d6f2": [
      6
    ],
    "5c84d600": [
      6
    ],
    "860959dc": [
      6
    ],
    "2ceb7755": [
      6
    ],
    "b4ecb890": [
      6
    ],
    "d461ed56": [
      6
    ],
    "7dfed537": [
      6
    ],
    "3a28cd1a": [
      6
    ],
    "0c740c50": [
      6
    ],
    "d21ea806": [
      6
    ],
    "136ed09e": [
      6
    ],
    "055e0827": [
      6
    ],
    "ba9e890c": [
      6
    ],
    "039f94df": [
      6
    ],
    "a5c76dc0": [
      6
    ],
    "1ea111e3": [
      6
    ],
    "1c461bab": [
      6
    ],
    "5c36fda7": [
      6
    ],
    "0004812c": [
      6
    ],
    "625d14f2": [
      3
    ],
    "50b8ce4f": [
      3
    ],
    "6cb812e6": [
      3
    ],
    "25b91e16": [
      3
    ],
    "b3a4ab36": [
      3
    ],
    "2f1a4c30": [
      3
    ],
    "17ab01b8": [
      3
    ],
    "0e2c786d": [
      3
    ],
    "4cae72ba": [
      3
    ],
    "ab736f98": [
      3
    ],
    "3df5b132": [
      3
    ],
    "70d118d6": [
      3
    ],
    "60ef6b66": [
      3
    ],
    "9fa3e42c": [
      3
    ],
    "39b4137b": [
      3
    ],
    "78488f0e": [
      11
    ],
    "1a65f875": [
      3
    ],
    "5a4e661a": [
      3
    ],
    "479b0591": [
      3
    ],
    "257a6b79": [
      3
    ],
    "ad4b9ca6": [
      3
    ],
    "30ecc614": [
      3
    ],
    "58cd090e": [
      3
    ],
    "41a564fa": [
      3
    ],
    "43963e1e": [
      3
    ],
    "062060b9": [
      3
    ],
    "ec3f260e": [
      3
    ],
    "2912e9d4": [
      3
    ],
    "ef68af4e": [
      3
    ],
    "cffe07e2": [
      3
    ],
    "7f09dda8": [
      3
    ],
    "534f003b": [
      11
    ],
    "b5ba45c2": [
      11
    ],
    "5c2b4f67": [
      3
    ],
    "4120a9b6": [
      11
    ],
    "3c558b84": [
      3
    ],
    "6d60a9e6": [
      3
    ],
    "5c5c4961": [
      3
    ],
    "38eea404": [
      3
    ],
    "0737165f": [
      3
    ],
    "7674ba22": [
      3
    ],
    "2a068b26": [
      3
    ],
    "53ec44d5": [
      3
    ],
    "3fb1fc29": [
      3
    ],
    "ef82e2ac": [
      3
    ],
    "a7293354": [
      3
    ],
    "bbbfd792": [
      3
    ],
    "353e865a": [
      11
    ],
    "0f1e5d9a": [
      6
    ],
    "cf133b68": [
      6
    ],
    "5cf79068": [
      11
    ],
    "00d2e914": [
      11
    ],
    "47c38d3d": [
      11
    ],
    "c6107440": [
      11
    ],
    "30fd43e0": [
      6
    ],
    "76bc1b61": [
      11
    ],
    "467c8500": [
      11
    ],
    "b4ecab5a": [
      11
    ],
    "583b181c": [
      11
    ],
    "59c349b6": [
      11
    ],
    "25c0cdaa": [
      11
    ],
    "32be746c": [
      11
    ],
    "ca184960": [
      6
    ],
    "23e48c16": [
      3
    ],
    "692a6ef6": [
      3
    ],
    "3d406deb": [
      3
    ],
    "21830cd2": [
      3
    ],
    "3ed07aa3": [
      3
    ],
    "652cc0fc": [
      3
    ],
    "76728f99": [
      3
    ],
    "4f38bb87": [
      3
    ],
    "296c9c76": [
      3
    ],
    "7dfccafc": [
      3
    ],
    "8c837ffa": [
      3
    ],
    "76ce9be2": [
      3
    ],
    "5483d0c9": [
      3
    ],
    "663da797": [
      3
    ],
    "15dc196c": [
      3
    ],
    "4e3e639d": [
      3
    ],
    "6ec27a8b": [
      3
    ],
    "978574be": [
      3
    ],
    "f1f9cf38": [
      3
    ],
    "52f3d859": [
      3
    ],
    "c7d2d75c": [
      3
    ],
    "f845de28": [
      3
    ],
    "113afdc8": [
      3
    ],
    "678bc18f": [
      3
    ],
    "6e7d000b": [
      3
    ],
    "ed3963e2": [
      3
    ],
    "56061c3c": [
      3
    ],
    "006e338f": [
      11
    ],
    "8e0a936a": [
      11
    ],
    "b9718920": [
      11
    ],
    "c2043c68": [
      3
    ],
    "76d6c261": [
      6
    ],
    "436c0cc0": [
      11
    ],
    "04d13da0": [
      3
    ],
    "258efaa9": [
      11
    ],
    "f3064c8c": [
      6
    ],
    "040fa653": [
      6
    ],
    "413fb8c4": [
      6
    ],
    "27ee89c6": [
      3
    ],
    "9da1053e": [
      3
    ],
    "4da38b63": [
      3
    ],
    "138f431a": [
      3
    ],
    "35b0ac93": [
      3
    ],
    "d61bd064": [
      3
    ],
    "18f23399": [
      3
    ],
    "66075b74": [
      3
    ],
    "558a04ab": [
      3
    ],
    "6dbd2748": [
      3
    ],
    "3f96155e": [
      3
    ],
    "7e5b26e0": [
      3
    ],
    "43b6990f": [
      3
    ],
    "6402caad": [
      3
    ],
    "850eead6": [
      3
    ],
    "8a2e078e": [
      3
    ],
    "709bc9ea": [
      3
    ],
    "6cff4f25": [
      3
    ],
    "c845d32e": [
      3
    ],
    "01ab91ad": [
      3
    ],
    "73e76614": [
      3
    ],
    "6cceffe4": [
      3
    ],
    "370a5847": [
      3
    ],
    "59f62101": [
      3
    ],
    "4aca5c1c": [
      3
    ],
    "509185a7": [
      3
    ],
    "6eb16894": [
      3
    ],
    "8842992e": [
      3
    ],
    "15c1aaf7": [
      3
    ],
    "2072c993": [
      3
    ],
    "c5b133e6": [
      3
    ],
    "797ee58f": [
      3
    ],
    "6f2cedba": [
      3
    ],
    "b12c33c8": [
      3
    ],
    "11a90a00": [
      3
    ],
    "54ccd99c": [
      3
    ],
    "48a1f424": [
      3
    ],
    "3232b699": [
      3
    ],
    "6638ee38": [
      3
    ],
    "29c90a25": [
      3
    ],
    "27c12b5a": [
      3
    ],
    "2753b44e": [
      3
    ],
    "b95c786c": [
      3
    ],
    "6af0761e": [
      3
    ],
    "a8cc2b50": [
      3
    ],
    "2148042f": [
      3
    ],
    "16aefd6e": [
      6
    ],
    "4f6fb0c6": [
      6
    ],
    "87798eda": [
      6
    ],
    "5558a7f3": [
      6
    ],
    "45cd5702": [
      6
    ],
    "330aea01": [
      6
    ],
    "76b5745c": [
      6
    ],
    "441842a8": [
      6
    ],
    "4f9e5bf1": [
      6
    ],
    "816370e0": [
      3
    ],
    "28f1822c": [
      3
    ],
    "c029f500": [
      3
    ],
    "31a764b8": [
      3
    ],
    "49213e02": [
      3
    ],
    "32fc5464": [
      3
    ],
    "19c1d6c7": [
      3
    ],
    "8716dc2a": [
      3
    ],
    "91ee718a": [
      11
    ],
    "11a4ebac": [
      3
    ],
    "03d9e7c6": [
      3
    ],
    "257701f9": [
      3
    ],
    "3c25be4f": [
      3
    ],
    "1903d38a": [
      3
    ],
    "16ab873e": [
      3
    ],
    "69aedb34": [
      3
    ],
    "b57e66a0": [
      3
    ],
    "03acb022": [
      3
    ],
    "4ebf042a": [
      11
    ],
    "22b6f984": [
      3
    ],
    "22b73515": [
      11
    ],
    "d34a147e": [
      3
    ],
    "dba6a10c": [
      11
    ],
    "80cb1a44": [
      11
    ],
    "eca21da0": [
      11
    ],
    "594ed007": [
      11
    ],
    "0333f4fa": [
      11
    ],
    "0ae7d552": [
      11
    ],
    "843b76dc": [
      6
    ],
    "1a16e3b3": [
      6
    ],
    "7d85ffd8": [
      11
    ],
    "23187ab2": [
      11
    ],
    "a01cd8e8": [
      11
    ],
    "4e13ed38": [
      11
    ],
    "ebad8926": [
      11
    ],
    "7bf6faaf": [
      11
    ],
    "1d5efe14": [
      11
    ],
    "5a93c125": [
      11
    ],
    "399b2d8a": [
      11
    ],
    "4e2e8446": [
      11
    ],
    "57330e42": [
      11
    ],
    "d3c08e26": [
      11
    ],
    "166e2134": [
      11
    ],
    "3f3b358a": [
      11
    ],
    "b3669ea6": [
      11
    ],
    "c0106482": [
      11
    ],
    "f211deee": [
      11
    ],
    "b6aac19a": [
      11
    ],
    "f9dc53fe": [
      11
    ],
    "699565d0": [
      11
    ],
    "710109f7": [
      11
    ],
    "ce081de0": [
      11
    ],
    "84febfee": [
      11
    ],
    "52fbc51e": [
      11
    ],
    "54717e96": [
      11
    ],
    "5883b597": [
      11
    ],
    "22caf48a": [
      11
    ],
    "24c26402": [
      11
    ],
    "000ffd9b": [
      11
    ],
    "0bc7a128": [
      11
    ],
    "01dcfb4a": [
      11
    ],
    "3f65fc86": [
      11
    ],
    "2c1f0069": [
      11
    ],
    "5511b55e": [
      11
    ],
    "48bf17f1": [
      11
    ],
    "020e3180": [
      11
    ],
    "34ed3ae6": [
      11
    ],
    "19abf1a8": [
      11
    ],
    "57eeb124": [
      11
    ],
    "4ec64e50": [
      11
    ],
    "bb7f2ca4": [
      11
    ],
    "6fd3cb05": [
      11
    ],
    "720ff096": [
      11
    ],
    "aee71daa": [
      11
    ],
    "50621b5c": [
      11
    ],
    "71d5e22c": [
      11
    ],
    "c276de4e": [
      11
    ],
    "6b8d8f81": [
      11
    ],
    "6b8ea729": [
      11
    ],
    "01e4baee": [
      11
    ],
    "5b11cbcc": [
      11
    ],
    "22184e44": [
      11
    ],
    "b64693fe": [
      11
    ],
    "e7b586fe": [
      11
    ],
    "51d0debb": [
      11
    ],
    "39e529c0": [
      11
    ],
    "010681f6": [
      11
    ],
    "e9f7ac44": [
      11
    ],
    "1398ca7a": [
      11
    ],
    "23deaeb0": [
      11
    ],
    "15dba9e0": [
      11
    ],
    "b71d07ce": [
      11
    ],
    "3d7a7208": [
      11
    ],
    "fa292fe4": [
      11
    ],
    "25c4b505": [
      11
    ],
    "0e0043d4": [
      11
    ],
    "eb5539be": [
      11
    ],
    "ce0b5236": [
      11
    ],
    "3f3d8137": [
      11
    ],
    "7ed87cd4": [
      11
    ],
    "11ed94b4": [
      11
    ],
    "01be138c": [
      11
    ],
    "5c7ab2de": [
      11
    ],
    "2d7c1c0e": [
      11
    ],
    "62a37db8": [
      11
    ],
    "3f46b8ab": [
      11
    ],
    "50ad1f36": [
      11
    ],
    "aac49ed2": [
      11
    ],
    "3de1329c": [
      11
    ],
    "27e8cf31": [
      11
    ],
    "313f4001": [
      11
    ],
    "40a1c0c3": [
      11
    ],
    "7dab2246": [
      11
    ],
    "502ce472": [
      11
    ],
    "7ed6c1a6": [
      11
    ],
    "488342fc": [
      11
    ],
    "5b7eb27c": [
      11
    ],
    "c8d06e1e": [
      11
    ],
    "52decb60": [
      11
    ],
    "ef3bd7ac": [
      11
    ],
    "7fe316dc": [
      11
    ],
    "ec8a3f68": [
      11
    ],
    "578bfc97": [
      11
    ],
    "878e52c0": [
      11
    ],
    "c2357f56": [
      11
    ],
    "0aa01b1f": [
      11
    ],
    "5ed38d43": [
      11
    ],
    "7eeffada": [
      11
    ],
    "c29c4254": [
      11
    ],
    "0bcbcb28": [
      11
    ],
    "5f44309b": [
      11
    ],
    "707c7337": [
      11
    ],
    "25aaf599": [
      11
    ],
    "15989b10": [
      11
    ],
    "e585c2a0": [
      11
    ],
    "421b2aba": [
      11
    ],
    "f79a9e80": [
      11
    ],
    "0b4c8b84": [
      11
    ],
    "9a5c07dc": [
      11
    ],
    "14e49eba": [
      11
    ],
    "2e0f4943": [
      11
    ],
    "db972a4e": [
      11
    ],
    "7d1d09be": [
      11
    ],
    "5ed814d6": [
      11
    ],
    "d9d32cb8": [
      11
    ],
    "00e8f89c": [
      11
    ],
    "5c994870": [
      11
    ],
    "06fbe669": [
      11
    ],
    "a605a6b8": [
      11
    ],
    "e8314794": [
      11
    ],
    "352911b6": [
      11
    ],
    "1ca40e56": [
      11
    ],
    "4940eb50": [
      11
    ],
    "8853b420": [
      11
    ],
    "0fedb936": [
      11
    ],
    "6f2c5e5b": [
      11
    ],
    "c8ceb488": [
      11
    ],
    "f0ef2bb0": [
      11
    ],
    "1ddc1ac8": [
      11
    ],
    "33ab1cc3": [
      11
    ],
    "1e3566b8": [
      11
    ],
    "48ff4f04": [
      11
    ],
    "7a31e048": [
      11
    ],
    "2897c391": [
      11
    ],
    "c3474104": [
      11
    ],
    "43c4ba17": [
      11
    ],
    "7356a188": [
      11
    ],
    "12f3c49c": [
      11
    ],
    "5c4b02ae": [
      11
    ],
    "6ed2aa38": [
      11
    ],
    "4f38cefe": [
      11
    ],
    "03f39375": [
      11
    ],
    "7469a4be": [
      11
    ],
    "5d84a439": [
      11
    ],
    "2c50cf13": [
      11
    ],
    "a2a74c0e": [
      11
    ],
    "7bd57890": [
      11
    ],
    "06e5ed65": [
      11
    ],
    "6e45c2a1": [
      11
    ],
    "91bfe972": [
      11
    ],
    "3a6f473f": [
      11
    ],
    "8cd712a0": [
      11
    ],
    "c7cb3026": [
      11
    ],
    "7c9d3c24": [
      11
    ],
    "22526d25": [
      11
    ],
    "d99cf276": [
      11
    ],
    "754039a9": [
      11
    ],
    "d90be6b6": [
      11
    ],
    "7bdde22b": [
      11
    ],
    "c5b888f6": [
      11
    ],
    "40a53f47": [
      11
    ],
    "1d3702ee": [
      11
    ],
    "4e3e6d8a": [
      11
    ],
    "0e91f411": [
      11
    ],
    "4e920005": [
      11
    ],
    "8c4f26f6": [
      11
    ],
    "a0acb626": [
      11
    ],
    "5277dd85": [
      11
    ],
    "240670d5": [
      11
    ],
    "3b60cff6": [
      11
    ],
    "460ebea5": [
      11
    ],
    "1f798d45": [
      11
    ],
    "f13c89b6": [
      11
    ],
    "81f3801e": [
      11
    ],
    "c0c7f9fc": [
      11
    ],
    "ae7d85bc": [
      11
    ],
    "0c91c416": [
      11
    ],
    "2a3b0591": [
      11
    ],
    "6d1c92d0": [
      11
    ],
    "fb5bbdf0": [
      11
    ],
    "4d2c3674": [
      11
    ],
    "1e73b0cc": [
      11
    ],
    "4f2f7865": [
      11
    ],
    "0bac7376": [
      11
    ],
    "6e411c26": [
      11
    ],
    "17aa54bf": [
      11
    ],
    "4a0c9342": [
      11
    ],
    "546e2f99": [
      11
    ],
    "a03bb5a6": [
      11
    ],
    "2926d5ee": [
      11
    ],
    "538ddb09": [
      11
    ],
    "95b44346": [
      11
    ],
    "173a2d1c": [
      11
    ],
    "e32c18d0": [
      11
    ],
    "5eef6ed8": [
      11
    ],
    "3ffc5ad0": [
      11
    ],
    "e90194ec": [
      11
    ],
    "fa4cb2c0": [
      11
    ],
    "02abf3b8": [
      11
    ],
    "646b4dae": [
      11
    ],
    "6cea549a": [
      11
    ],
    "0725268a": [
      11
    ],
    "04286ebe": [
      11
    ],
    "55d22b54": [
      11
    ],
    "2b6eb2b2": [
      11
    ],
    "46985d3a": [
      11
    ],
    "e662ec06": [
      11
    ],
    "e915fb2a": [
      11
    ],
    "16702b6a": [
      11
    ],
    "d7450d96": [
      11
    ],
    "0f4dc041": [
      11
    ],
    "8d0bcc28": [
      11
    ],
    "3edd5721": [
      11
    ],
    "7db36171": [
      11
    ],
    "897dc342": [
      11
    ],
    "5c8c687f": [
      11
    ],
    "5ee0e99f": [
      11
    ],
    "67c8f34e": [
      11
    ],
    "04cfb0d2": [
      11
    ],
    "a507f9fc": [
      11
    ],
    "40cb4c64": [
      11
    ],
    "46650ef7": [
      11
    ],
    "96cb3b1a": [
      11
    ],
    "b26b0d76": [
      11
    ],
    "4c19929a": [
      11
    ],
    "cb1c08ce": [
      11
    ],
    "87ab91b6": [
      11
    ],
    "5122090a": [
      11
    ],
    "7b464f69": [
      11
    ],
    "4b4fbede": [
      11
    ],
    "a93e4eae": [
      11
    ],
    "3d16ac79": [
      11
    ],
    "66ddbaf8": [
      11
    ],
    "06b242d6": [
      11
    ],
    "ffa8303c": [
      11
    ],
    "64ae14ee": [
      11
    ],
    "0a170874": [
      11
    ],
    "03750071": [
      11
    ],
    "1c017deb": [
      11
    ],
    "5f0f6f03": [
      11
    ],
    "29b411f7": [
      11
    ],
    "ce3950d4": [
      11
    ],
    "b6bdc88a": [
      11
    ],
    "07a519b4": [
      11
    ],
    "17aabb3c": [
      11
    ],
    "48ea4518": [
      11
    ],
    "59ac8712": [
      11
    ],
    "636aabe2": [
      11
    ],
    "065788c3": [
      11
    ],
    "a6b967aa": [
      11
    ],
    "6f96a4b8": [
      11
    ],
    "23afc81a": [
      11
    ],
    "5e601045": [
      11
    ],
    "315225c5": [
      11
    ],
    "4a5a48ba": [
      11
    ],
    "51d6cb5e": [
      11
    ],
    "95dafffc": [
      11
    ],
    "3c511f6d": [
      11
    ],
    "c223e222": [
      11
    ],
    "7cbdda2d": [
      11
    ],
    "e6b70ee6": [
      11
    ],
    "c567512a": [
      11
    ],
    "2fb78e64": [
      11
    ],
    "1af67c38": [
      11
    ],
    "67d2284e": [
      11
    ],
    "655db332": [
      11
    ],
    "8b2ed1d0": [
      11
    ],
    "5e8f2a2b": [
      11
    ],
    "7cdb4a38": [
      11
    ],
    "5d1335b8": [
      11
    ],
    "2e5736af": [
      11
    ],
    "3be835bf": [
      11
    ],
    "88b23ba6": [
      11
    ],
    "7fb764c6": [
      11
    ],
    "128f2688": [
      11
    ],
    "4317832f": [
      11
    ],
    "d205511e": [
      11
    ],
    "6d307c4b": [
      11
    ],
    "aab84eaa": [
      11
    ],
    "b1771fc4": [
      11
    ],
    "e137241e": [
      11
    ],
    "79dc7039": [
      11
    ],
    "2070ae42": [
      11
    ],
    "31f7b266": [
      11
    ],
    "6101af6d": [
      11
    ],
    "213b511d": [
      11
    ],
    "27aa9a8d": [
      11
    ],
    "5bd267c9": [
      11
    ],
    "55bd97e2": [
      11
    ],
    "1f6541ea": [
      11
    ],
    "26b5ada0": [
      11
    ],
    "9bc0befc": [
      11
    ],
    "64e58a68": [
      11
    ],
    "324c4cd9": [
      11
    ],
    "4bc3cc50": [
      11
    ],
    "7edcad98": [
      11
    ],
    "427caedb": [
      11
    ],
    "dff3d18e": [
      11
    ],
    "52f1f03a": [
      11
    ],
    "c21b08ee": [
      11
    ],
    "fca758e2": [
      11
    ],
    "4ecebde4": [
      11
    ],
    "12fe55ec": [
      11
    ],
    "7e88a735": [
      11
    ],
    "2a52848a": [
      11
    ],
    "589318fc": [
      11
    ],
    "5d79b460": [
      11
    ],
    "07ff5c49": [
      11
    ],
    "9acc4c78": [
      11
    ],
    "93ddf138": [
      11
    ],
    "4a015c64": [
      11
    ],
    "03883ce4": [
      11
    ],
    "9647dea0": [
      11
    ],
    "51d5afde": [
      11
    ],
    "8e0559a4": [
      11
    ],
    "18e4a29c": [
      11
    ],
    "c784fab0": [
      11
    ],
    "24fa12b2": [
      11
    ],
    "49f0207f": [
      6
    ],
    "0cfe57e5": [
      6
    ],
    "2dc03ca8": [
      6
    ],
    "c2f310ba": [
      6
    ],
    "8025c064": [
      11
    ],
    "11ffe0f0": [
      6
    ],
    "33c1695a": [
      3
    ],
    "41815d7b": [
      3
    ],
    "8494c184": [
      3
    ],
    "06ccb8d0": [
      3
    ],
    "e1c98bc0": [
      3
    ],
    "92c37f16": [
      3
    ],
    "e364f82e": [
      3
    ],
    "6fbaf064": [
      3
    ],
    "44dad2be": [
      3
    ],
    "7ada6610": [
      3
    ],
    "121a28a8": [
      3
    ],
    "44388d40": [
      3
    ],
    "1e90fc16": [
      3
    ],
    "7b386fca": [
      3
    ],
    "77aa87a1": [
      3
    ],
    "5cb7f3d1": [
      3
    ],
    "34e201ee": [
      3
    ],
    "ae36015a": [
      3
    ],
    "7c598a58": [
      3
    ],
    "c3dfee8e": [
      3
    ],
    "384e52ee": [
      3
    ],
    "65bc1e3b": [
      3
    ],
    "194078a8": [
      3
    ],
    "2e6da624": [
      3
    ],
    "27d3414e": [
      3
    ],
    "e8b54312": [
      3
    ],
    "5c717628": [
      3
    ],
    "a54b7b84": [
      3
    ],
    "24bf17d4": [
      3
    ],
    "2fc31982": [
      3
    ],
    "858cdec8": [
      3
    ],
    "73c2ce66": [
      3
    ],
    "77100e81": [
      3
    ],
    "eb324a2c": [
      3
    ],
    "c1147092": [
      3
    ],
    "35efd8fa": [
      3
    ],
    "835cd800": [
      6
    ],
    "6b3938e9": [
      6
    ],
    "219f61af": [
      6
    ],
    "fa6e5648": [
      11
    ],
    "3b8aab7e": [
      11
    ],
    "cadc10de": [
      6
    ],
    "d447bf9c": [
      6
    ],
    "8cdb287e": [
      6
    ],
    "fc9d9090": [
      6
    ],
    "42f12115": [
      6
    ],
    "b7342f9c": [
      6
    ],
    "8780e8be": [
      6
    ],
    "67bde5be": [
      6
    ],
    "20a36323": [
      6
    ],
    "fbcfab80": [
      6
    ],
    "3c2c1f7a": [
      6
    ],
    "09503bfd": [
      6
    ],
    "5a25bbd6": [
      6
    ],
    "0a48c8ca": [
      6
    ],
    "4cc4c266": [
      6
    ],
    "1515070f": [
      6
    ],
    "3b8db8dc": [
      6
    ],
    "38f41dd8": [
      6
    ],
    "63b4b914": [
      3
    ],
    "25d3420b": [
      3
    ],
    "4b11ff25": [
      3
    ],
    "191c38cc": [
      3
    ],
    "352aaf2b": [
      3
    ],
    "2f11c87c": [
      3
    ],
    "721a395a": [
      11
    ],
    "7af6ee76": [
      11
    ],
    "619e06fa": [
      11
    ],
    "f92764e4": [
      11
    ],
    "1756c05a": [
      3
    ],
    "225e99e2": [
      3
    ],
    "22f2d652": [
      3
    ],
    "13dc1813": [
      3
    ],
    "46f3609e": [
      3
    ],
    "23d568ba": [
      3
    ],
    "875762a0": [
      3
    ],
    "125d1d14": [
      3
    ],
    "4e7aaa06": [
      3
    ],
    "77a8efa2": [
      3
    ],
    "2abfab47": [
      3
    ],
    "a6b1fdcc": [
      3
    ],
    "544d5d71": [
      3
    ],
    "729a15e1": [
      11
    ],
    "5ae4ec10": [
      11
    ],
    "6ed40575": [
      11
    ],
    "3b8a4ef5": [
      11
    ],
    "59f417c8": [
      11
    ],
    "6b8f8542": [
      11
    ],
    "c1573e8a": [
      11
    ],
    "2a1a52a3": [
      11
    ],
    "4532a851": [
      11
    ],
    "1ba0b61f": [
      11
    ],
    "3e6e4af5": [
      6
    ],
    "5b77340e": [
      11
    ],
    "9e58608c": [
      3
    ],
    "4c1339b6": [
      3
    ],
    "2f52f84b": [
      3
    ],
    "50777d34": [
      3
    ],
    "10dfd376": [
      3
    ],
    "ab7482bc": [
      3
    ],
    "4f3602f4": [
      3
    ],
    "1ac0c7f0": [
      3
    ],
    "08fa5578": [
      3
    ],
    "c4566fce": [
      3
    ],
    "2a3522b9": [
      3
    ],
    "5d8a4678": [
      3
    ],
    "3b051d58": [
      3
    ],
    "bed57054": [
      3
    ],
    "464fd5d5": [
      3
    ],
    "3f0c6412": [
      3
    ],
    "25b5db3e": [
      3
    ],
    "69c00534": [
      3
    ],
    "12f5660b": [
      3
    ],
    "db691a70": [
      3
    ],
    "63a9755a": [
      3
    ],
    "6ebc331e": [
      3
    ],
    "31c80e30": [
      3
    ],
    "f86983fc": [
      3
    ],
    "f6e4d134": [
      3
    ],
    "5153d343": [
      11
    ],
    "ed6d9a30": [
      11
    ],
    "4f7b67d0": [
      3
    ],
    "f738afe8": [
      3
    ],
    "589ccc54": [
      3
    ],
    "7f9eeedc": [
      3
    ],
    "59f1c893": [
      3
    ],
    "aaa29586": [
      3
    ],
    "5cad9379": [
      11
    ],
    "591de86f": [
      11
    ],
    "6eff4b68": [
      11
    ],
    "fea2adf4": [
      11
    ],
    "bc84bc6c": [
      11
    ],
    "04a91676": [
      11
    ],
    "8fc9491a": [
      11
    ],
    "17f8f75c": [
      11
    ],
    "01c8d958": [
      11
    ],
    "1684076b": [
      11
    ],
    "05a1b534": [
      11
    ],
    "63bb4a28": [
      11
    ],
    "2109f554": [
      11
    ],
    "7d8a585c": [
      11
    ],
    "6c3b117e": [
      11
    ],
    "630fb012": [
      6
    ],
    "fbc3cdfe": [
      6
    ],
    "6d4973aa": [
      6
    ],
    "bf654c70": [
      6
    ],
    "55199ff1": [
      6
    ],
    "cf173164": [
      6
    ],
    "3f3b50b6": [
      6
    ],
    "99c5579a": [
      6
    ],
    "02dccf28": [
      6
    ],
    "ca24ff0c": [
      6
    ],
    "6c6ab6a3": [
      6
    ],
    "2eb51850": [
      6
    ],
    "79caf5f4": [
      6
    ],
    "53241f2e": [
      6
    ],
    "55603cc2": [
      6
    ],
    "b8248ad4": [
      6
    ],
    "75b13e08": [
      6
    ],
    "6d371015": [
      6
    ],
    "2f984691": [
      6
    ],
    "79f6e4bf": [
      6
    ],
    "21afbcd8": [
      6
    ],
    "89d5487a": [
      11
    ],
    "b818ce00": [
      11
    ],
    "11747ff0": [
      11
    ],
    "157b43bc": [
      16
    ],
    "e23c667a": [
      16
    ],
    "5823d578": [
      16
    ],
    "074c4113": [
      2
    ],
    "c2f74320": [
      7
    ],
    "26b17343": [
      15
    ],
    "2a20f892": [
      14
    ],
    "4e549428": [
      18
    ],
    "5e21d476": [
      9
    ],
    "415e44ae": [
      4
    ],
    "98e857cc": [
      16
    ],
    "dff26212": [
      16
    ],
    "72b8fc35": [
      2
    ],
    "6c3d9f5c": [
      2
    ],
    "3ca24ddc": [
      7
    ],
    "0f9a79ef": [
      7
    ],
    "e212e236": [
      15
    ],
    "5fe72642": [
      15
    ],
    "4ef0064e": [
      14
    ],
    "39fcc3f6": [
      14
    ],
    "0a0ae0ec": [
      18
    ],
    "eaf9eb66": [
      18
    ],
    "5b512c14": [
      9
    ],
    "f813cc52": [
      9
    ],
    "0175b747": [
      4
    ],
    "de039bec": [
      4
    ],
    "7afdcaca": [
      16
    ],
    "2f844a5e": [
      16
    ],
    "b3337ab6": [
      16
    ],
    "3f2b8ca0": [
      12
    ],
    "af45fc90": [
      2
    ],
    "3966a082": [
      2
    ],
    "48e6bdee": [
      2
    ],
    "4c30a786": [
      2
    ],
    "d515f760": [
      2
    ],
    "4ea226ba": [
      7
    ],
    "d206f284": [
      7
    ],
    "087f9347": [
      7
    ],
    "56c1a8c5": [
      7
    ],
    "2c477e64": [
      7
    ],
    "73c3c52c": [
      15
    ],
    "8120622a": [
      15
    ],
    "82acbed2": [
      15
    ],
    "02ad0c72": [
      15
    ],
    "3810299e": [
      15
    ],
    "607849fc": [
      14
    ],
    "967792da": [
      14
    ],
    "01923145": [
      14
    ],
    "5a19114c": [
      14
    ],
    "2d3b44e8": [
      14
    ],
    "6c0251c5": [
      18
    ],
    "1e9b47f4": [
      18
    ],
    "e3edfdb8": [
      18
    ],
    "29917adf": [
      18
    ],
    "813a7206": [
      18
    ],
    "be01065e": [
      9
    ],
    "5b93d124": [
      9
    ],
    "40bc5f98": [
      9
    ],
    "1b67d8fd": [
      9
    ],
    "14bbe31e": [
      9
    ],
    "3d584d38": [
      4
    ],
    "3925324b": [
      4
    ],
    "72b00b36": [
      4
    ],
    "0ffc7f84": [
      4
    ]
  },
  "assetsMapping": {
    "67c13ec2": [
      "13c39e1.modern.js"
    ],
    "085a35c4": [
      "157e5a7.modern.js"
    ],
    "349edf93": [
      "1bf87da.modern.js"
    ],
    "6fca0322": [
      "31d3a40.modern.js"
    ],
    "1a3ae26b": [
      "588bc92.modern.js"
    ],
    "3618f2e1": [
      "5b5ff44.modern.js"
    ],
    "ed267066": [
      "629f580.modern.js"
    ],
    "4d45c734": [
      "6ec9b55.modern.js"
    ],
    "2cf24018": [
      "74e7225.modern.js"
    ],
    "7ea24c87": [
      "90e3a87.modern.js"
    ],
    "bba68bf6": [
      "941945c.modern.js"
    ],
    "057cd9c4": [
      "a15f9a5.modern.js"
    ],
    "2a130dde": [
      "bec7cb8.modern.js"
    ],
    "2aff1868": [
      "c15d5f1.modern.js"
    ],
    "122449dc": [
      "e694531.modern.js"
    ],
    "749c2580": [
      "f6d72cb.modern.js"
    ],
    "79980e3a": [
      "fdf6858.modern.js"
    ]
  }
}