{
  "publicPath": "/_nuxt/",
  "all": [
    "../server/index.spa.html",
    "08299eb.modern.js",
    "095152e.modern.js",
    "4cd3ef3.modern.js",
    "51645e0.modern.js",
    "564bc53.modern.js",
    "78091c1.modern.js",
    "7f52467.modern.js",
    "8f7831f.modern.js",
    "9c18ccf.modern.js",
    "LICENSES",
    "b567b5a.modern.js",
    "bef9e6b.modern.js",
    "cc3b544.modern.js",
    "dc75398.modern.js",
    "dc95ba1.modern.js",
    "e9b90e8.modern.js"
  ],
  "initial": [
    "7f52467.modern.js",
    "e9b90e8.modern.js",
    "dc95ba1.modern.js",
    "dc75398.modern.js"
  ],
  "async": [
    "08299eb.modern.js",
    "095152e.modern.js",
    "4cd3ef3.modern.js",
    "51645e0.modern.js",
    "564bc53.modern.js",
    "78091c1.modern.js",
    "8f7831f.modern.js",
    "9c18ccf.modern.js",
    "b567b5a.modern.js",
    "bef9e6b.modern.js",
    "cc3b544.modern.js"
  ],
  "modules": {
    "10010952": [
      15
    ],
    "12754340": [
      15
    ],
    "13355845": [
      16
    ],
    "17420972": [
      15
    ],
    "26069005": [
      16
    ],
    "26674108": [
      16
    ],
    "29539102": [
      14
    ],
    "39401580": [
      14
    ],
    "46438990": [
      15
    ],
    "52054224": [
      15
    ],
    "58023272": [
      15
    ],
    "60919010": [
      16
    ],
    "61235026": [
      16
    ],
    "61530775": [
      16
    ],
    "66487086": [
      1
    ],
    "78005846": [
      15
    ],
    "79853240": [
      15
    ],
    "e9c18b52": [
      16
    ],
    "4888ae46": [
      15
    ],
    "88c3c2dc": [
      14
    ],
    "18055b1c": [
      15
    ],
    "1b1c8faa": [
      16
    ],
    "77850e6f": [
      16
    ],
    "768ec390": [
      15
    ],
    "b10ec3c8": [
      15
    ],
    "22cacc68": [
      16
    ],
    "951720b4": [
      16
    ],
    "0c533260": [
      16
    ],
    "149736b2": [
      16
    ],
    "28c3a4da": [
      16
    ],
    "372bbe7c": [
      16
    ],
    "1858e2ed": [
      16
    ],
    "3a485eb1": [
      15
    ],
    "691f90ee": [
      16
    ],
    "58ff537e": [
      16
    ],
    "1f0251b2": [
      16
    ],
    "7ce140e3": [
      16
    ],
    "3c5b0b9c": [
      16
    ],
    "4b78439e": [
      15
    ],
    "1d2a39f9": [
      16
    ],
    "4ad1abbe": [
      16
    ],
    "57a01b42": [
      16
    ],
    "e37b569c": [
      15
    ],
    "03c2b977": [
      15
    ],
    "7ac0961d": [
      16
    ],
    "44fe1c52": [
      16
    ],
    "30044a48": [
      16
    ],
    "a01db77a": [
      15
    ],
    "27a63847": [
      15
    ],
    "af75e984": [
      15
    ],
    "0a6ec97f": [
      16
    ],
    "5d9ee83f": [
      16
    ],
    "7157741d": [
      15
    ],
    "7278f3ce": [
      15
    ],
    "435b781f": [
      15
    ],
    "34b558dd": [
      16
    ],
    "52189c74": [
      16
    ],
    "d27bf25e": [
      14
    ],
    "7bbcd0a2": [
      14
    ],
    "49d260ea": [
      14
    ],
    "66ba26cb": [
      14
    ],
    "7b5d358c": [
      14
    ],
    "6861b642": [
      14
    ],
    "1331ef3c": [
      14
    ],
    "4389dd8a": [
      14
    ],
    "71c9d0ad": [
      14
    ],
    "4e2ff7db": [
      14
    ],
    "1a0ca3a2": [
      14
    ],
    "5cd0cda8": [
      14
    ],
    "d36dba8c": [
      14
    ],
    "063946fd": [
      14
    ],
    "62a22960": [
      14
    ],
    "3389a2a6": [
      14
    ],
    "5cf67cdf": [
      14
    ],
    "4b23bb34": [
      14
    ],
    "a3ff7914": [
      14
    ],
    "17229d3f": [
      14
    ],
    "96f18540": [
      14
    ],
    "c4ca9244": [
      14
    ],
    "5e329c2c": [
      14
    ],
    "9d94fefc": [
      14
    ],
    "c70a55ae": [
      14
    ],
    "7c934efe": [
      14
    ],
    "1e3483b8": [
      14
    ],
    "33c3005a": [
      14
    ],
    "11cf9237": [
      14
    ],
    "b7075b3c": [
      16
    ],
    "7dfe94e6": [
      16
    ],
    "140529e8": [
      16
    ],
    "290818f9": [
      16
    ],
    "0a626e32": [
      15
    ],
    "cad3cb5a": [
      16
    ],
    "76e4f616": [
      16
    ],
    "f47e67ee": [
      16
    ],
    "0b7e1990": [
      16
    ],
    "e20aabb8": [
      16
    ],
    "7eed6360": [
      16
    ],
    "ef484db2": [
      15
    ],
    "6d2a73d3": [
      16
    ],
    "5e410c89": [
      16
    ],
    "3f00128d": [
      16
    ],
    "389c8bee": [
      15
    ],
    "7b9789f1": [
      15
    ],
    "0f9c569c": [
      16
    ],
    "2844cf57": [
      16
    ],
    "99d25898": [
      16
    ],
    "cc97a6d2": [
      16
    ],
    "70e8fb36": [
      16
    ],
    "3f15499c": [
      16
    ],
    "f19be3c8": [
      16
    ],
    "16cd7d12": [
      16
    ],
    "037cca32": [
      16
    ],
    "70c72453": [
      16
    ],
    "c11fe6ae": [
      16
    ],
    "534c4d93": [
      15
    ],
    "6351e8c8": [
      15
    ],
    "01b1968a": [
      16
    ],
    "4e470fee": [
      16
    ],
    "74e08950": [
      16
    ],
    "7ebfb144": [
      16
    ],
    "0a715db9": [
      16
    ],
    "a1e1f4be": [
      16
    ],
    "52a5a61c": [
      16
    ],
    "60a5d390": [
      16
    ],
    "6b4330d2": [
      16
    ],
    "e6638c9a": [
      16
    ],
    "2247ec54": [
      16
    ],
    "2f1fe08c": [
      16
    ],
    "660a6ae7": [
      16
    ],
    "ae767d5a": [
      16
    ],
    "143ad6af": [
      16
    ],
    "8873079e": [
      16
    ],
    "9e015086": [
      15
    ],
    "047224be": [
      15
    ],
    "fe961eda": [
      15
    ],
    "3eb8a520": [
      15
    ],
    "3bae3c1d": [
      15
    ],
    "b09de99a": [
      15
    ],
    "21559dd5": [
      14
    ],
    "48d8805f": [
      14
    ],
    "4ea97dc0": [
      15
    ],
    "7b575cd9": [
      15
    ],
    "3d679d7a": [
      15
    ],
    "6efa9fb2": [
      15
    ],
    "bb1ae4f0": [
      14
    ],
    "32e5a4b4": [
      15
    ],
    "32b64aa6": [
      15
    ],
    "0c0bc4f4": [
      15
    ],
    "3d36103a": [
      15
    ],
    "6709bfef": [
      15
    ],
    "62b5cc5c": [
      15
    ],
    "3e258a44": [
      15
    ],
    "0507ac08": [
      15
    ],
    "8fbeee10": [
      14
    ],
    "d95b529c": [
      16
    ],
    "628c7930": [
      16
    ],
    "b48fd0b0": [
      16
    ],
    "24e5bcd8": [
      16
    ],
    "3cc190ff": [
      16
    ],
    "235512d6": [
      16
    ],
    "3ea69fea": [
      16
    ],
    "925fed30": [
      16
    ],
    "835988b6": [
      16
    ],
    "47bcb034": [
      16
    ],
    "43f1b52c": [
      16
    ],
    "6d112288": [
      16
    ],
    "0b824454": [
      16
    ],
    "9ae824c4": [
      16
    ],
    "ad32ff72": [
      16
    ],
    "c913e3ec": [
      16
    ],
    "3c744608": [
      16
    ],
    "679cebf5": [
      16
    ],
    "30bf9429": [
      16
    ],
    "00a8e22b": [
      16
    ],
    "63e51c8c": [
      16
    ],
    "55e53cf0": [
      16
    ],
    "6b18492b": [
      16
    ],
    "e53d7768": [
      16
    ],
    "b8fc0686": [
      16
    ],
    "0018a7b2": [
      15
    ],
    "8eb5ab24": [
      15
    ],
    "2f510526": [
      15
    ],
    "7df2dd49": [
      16
    ],
    "cb11ebde": [
      15
    ],
    "4b37a940": [
      15
    ],
    "72c7a90f": [
      15
    ],
    "3018be9c": [
      15
    ],
    "7f8c1b40": [
      15
    ],
    "0fca5956": [
      15
    ],
    "122137fc": [
      15
    ],
    "6ed8e7fb": [
      15
    ],
    "edc9588e": [
      14
    ],
    "151a167a": [
      15
    ],
    "0833eda6": [
      16
    ],
    "37261be8": [
      15
    ],
    "6ebbb08d": [
      14
    ],
    "1a27c6ba": [
      14
    ],
    "72c5bef6": [
      14
    ],
    "02296cc0": [
      16
    ],
    "4af52c86": [
      16
    ],
    "7f0b113d": [
      16
    ],
    "3a85539a": [
      16
    ],
    "53d00f31": [
      16
    ],
    "83925f54": [
      16
    ],
    "66a336e5": [
      16
    ],
    "6a168245": [
      16
    ],
    "2c4e3ab3": [
      16
    ],
    "54716df2": [
      16
    ],
    "3a1ff52a": [
      16
    ],
    "5370af10": [
      16
    ],
    "6113ecc4": [
      16
    ],
    "c7dacc98": [
      16
    ],
    "39395bf8": [
      16
    ],
    "602d98f6": [
      16
    ],
    "36d9dff0": [
      16
    ],
    "ec3f77bc": [
      16
    ],
    "67636e0c": [
      16
    ],
    "518ef076": [
      16
    ],
    "257c78a4": [
      16
    ],
    "3a38407f": [
      16
    ],
    "161ff3d6": [
      16
    ],
    "69f7cb7e": [
      16
    ],
    "0e216ab5": [
      16
    ],
    "382512da": [
      16
    ],
    "47754ecc": [
      16
    ],
    "8ac90512": [
      16
    ],
    "1a4f144e": [
      16
    ],
    "0116ee63": [
      16
    ],
    "0bdd134e": [
      16
    ],
    "837a5a0a": [
      16
    ],
    "4f13ab96": [
      16
    ],
    "799e284a": [
      16
    ],
    "a22e358a": [
      16
    ],
    "15613c70": [
      16
    ],
    "0d7d01d4": [
      16
    ],
    "17d2f95b": [
      16
    ],
    "e6785b5c": [
      16
    ],
    "300fc762": [
      14
    ],
    "478d33a4": [
      14
    ],
    "9b31c05c": [
      14
    ],
    "0adab1b7": [
      14
    ],
    "84aeb606": [
      14
    ],
    "d3ff639c": [
      14
    ],
    "b98649ce": [
      14
    ],
    "2d6154e6": [
      16
    ],
    "2f9149a9": [
      16
    ],
    "70abdc76": [
      16
    ],
    "67dd2032": [
      16
    ],
    "43b72947": [
      16
    ],
    "20619e44": [
      16
    ],
    "3303b330": [
      16
    ],
    "7b693710": [
      15
    ],
    "a08347d6": [
      15
    ],
    "408d9be8": [
      15
    ],
    "140e7f27": [
      16
    ],
    "2d0e1643": [
      16
    ],
    "22c8a31c": [
      16
    ],
    "6559eccc": [
      16
    ],
    "80fd3d26": [
      16
    ],
    "1dde6ade": [
      16
    ],
    "2e26f452": [
      16
    ],
    "01fb581f": [
      16
    ],
    "c3741794": [
      15
    ],
    "39ac2128": [
      15
    ],
    "6f47f567": [
      15
    ],
    "7b157474": [
      15
    ],
    "4514f87e": [
      15
    ],
    "d5e95afe": [
      15
    ],
    "4c44efcb": [
      15
    ],
    "2c57ee7c": [
      15
    ],
    "5262d304": [
      15
    ],
    "0c30407a": [
      15
    ],
    "b0465f46": [
      15
    ],
    "c8a0702c": [
      15
    ],
    "cad59786": [
      15
    ],
    "3cf595ab": [
      15
    ],
    "4be94ba4": [
      15
    ],
    "033353e2": [
      15
    ],
    "5534e4bb": [
      16
    ],
    "01ac3092": [
      15
    ],
    "c5216692": [
      15
    ],
    "01a2299b": [
      15
    ],
    "f94f36f8": [
      15
    ],
    "1a5cf01d": [
      15
    ],
    "2c465e62": [
      15
    ],
    "eb20938c": [
      14
    ],
    "4a520d80": [
      15
    ],
    "6f45d122": [
      15
    ],
    "f228e7be": [
      15
    ],
    "979a602c": [
      15
    ],
    "49ed63ec": [
      15
    ],
    "61c7459a": [
      15
    ],
    "71bcbc48": [
      15
    ],
    "4fbbdf2d": [
      15
    ],
    "02f2525a": [
      15
    ],
    "fd97c782": [
      15
    ],
    "f2131160": [
      15
    ],
    "1bc466d2": [
      15
    ],
    "02c5cd1e": [
      15
    ],
    "744319ea": [
      15
    ],
    "91be6e3c": [
      15
    ],
    "961d2db4": [
      15
    ],
    "77b3b072": [
      15
    ],
    "591767a7": [
      15
    ],
    "31d1d8c7": [
      15
    ],
    "747ba472": [
      15
    ],
    "ff3b2f5a": [
      15
    ],
    "2283b7ce": [
      15
    ],
    "5e41efeb": [
      15
    ],
    "bcf99d22": [
      15
    ],
    "7fe25200": [
      15
    ],
    "5968264f": [
      15
    ],
    "6bbbdc7e": [
      14
    ],
    "8b585834": [
      14
    ],
    "532c1e10": [
      14
    ],
    "311aa9c8": [
      14
    ],
    "87730a6a": [
      15
    ],
    "00330ce0": [
      14
    ],
    "3fd00578": [
      16
    ],
    "4c87a3e1": [
      16
    ],
    "7b75eee4": [
      16
    ],
    "7ff1f883": [
      16
    ],
    "405b221c": [
      16
    ],
    "f50cdbe4": [
      16
    ],
    "0a66425b": [
      16
    ],
    "41342dbb": [
      16
    ],
    "134c8dc7": [
      16
    ],
    "f4761f62": [
      16
    ],
    "2a4f0d15": [
      16
    ],
    "4660bdb3": [
      16
    ],
    "33a671a3": [
      16
    ],
    "23edb9d0": [
      16
    ],
    "7791cac7": [
      16
    ],
    "79cdd144": [
      16
    ],
    "31bca107": [
      16
    ],
    "60b5ea0e": [
      16
    ],
    "16881d00": [
      16
    ],
    "bf445fde": [
      16
    ],
    "548f7be4": [
      16
    ],
    "94a21a18": [
      16
    ],
    "27f7cdcb": [
      16
    ],
    "5138528a": [
      16
    ],
    "2821c7da": [
      16
    ],
    "4eaed4bc": [
      16
    ],
    "23c9f219": [
      16
    ],
    "20a551a3": [
      16
    ],
    "1a5e4038": [
      16
    ],
    "45f3559a": [
      16
    ],
    "122db926": [
      14
    ],
    "12c2a66c": [
      14
    ],
    "a2bc121c": [
      14
    ],
    "3aa49196": [
      14
    ],
    "723f1820": [
      15
    ],
    "c4e704f0": [
      15
    ],
    "6af86f72": [
      14
    ],
    "7724b054": [
      14
    ],
    "e3b798e4": [
      14
    ],
    "139c196a": [
      14
    ],
    "233ab783": [
      14
    ],
    "22a9c85a": [
      14
    ],
    "1a87c26e": [
      14
    ],
    "5eeb3319": [
      14
    ],
    "337dffd4": [
      14
    ],
    "54d6fbe6": [
      14
    ],
    "d56d0cd4": [
      14
    ],
    "d244e266": [
      14
    ],
    "3979b47d": [
      14
    ],
    "4f233648": [
      15
    ],
    "01d6c3e4": [
      16
    ],
    "1af28492": [
      16
    ],
    "186ca970": [
      16
    ],
    "993c0c6e": [
      16
    ],
    "12f68b68": [
      16
    ],
    "0f453e42": [
      16
    ],
    "4157ce57": [
      16
    ],
    "33adab35": [
      16
    ],
    "8d898588": [
      16
    ],
    "7b631294": [
      16
    ],
    "22a30c01": [
      16
    ],
    "83c9ac92": [
      16
    ],
    "d0acdeda": [
      16
    ],
    "dcf69f5c": [
      16
    ],
    "088b8784": [
      16
    ],
    "5a9c83d7": [
      16
    ],
    "22d9c324": [
      16
    ],
    "96bc66c4": [
      15
    ],
    "9cfaf516": [
      15
    ],
    "6dc32658": [
      15
    ],
    "3a796fd8": [
      15
    ],
    "771ac09c": [
      15
    ],
    "073529c4": [
      15
    ],
    "29c4c6c6": [
      15
    ],
    "bbaab418": [
      15
    ],
    "1144c65c": [
      15
    ],
    "705c1696": [
      14
    ],
    "44f1f994": [
      15
    ],
    "07136b2c": [
      15
    ],
    "b9dbde2e": [
      15
    ],
    "1666ec35": [
      15
    ],
    "1f928d49": [
      15
    ],
    "791cd593": [
      15
    ],
    "f3c29bea": [
      15
    ],
    "3f5c788e": [
      15
    ],
    "f75d7cb6": [
      15
    ],
    "b0d8264e": [
      15
    ],
    "09e5d3be": [
      15
    ],
    "1d7e732d": [
      15
    ],
    "1563eb59": [
      15
    ],
    "f516f8d4": [
      15
    ],
    "7675dd09": [
      15
    ],
    "0dcbcd5d": [
      16
    ],
    "60cb193c": [
      16
    ],
    "32a1f32e": [
      16
    ],
    "53da2d3a": [
      16
    ],
    "b71accfc": [
      16
    ],
    "6c16f7f1": [
      16
    ],
    "9d04d92a": [
      16
    ],
    "a110394a": [
      16
    ],
    "4ab74b56": [
      16
    ],
    "14890b48": [
      16
    ],
    "7eae7db2": [
      16
    ],
    "3e67cd5e": [
      16
    ],
    "b8377a8e": [
      16
    ],
    "43a176f8": [
      16
    ],
    "c7f73c96": [
      16
    ],
    "cbf0d4c4": [
      16
    ],
    "5b90a21e": [
      16
    ],
    "11440e08": [
      16
    ],
    "168357c4": [
      15
    ],
    "d36d2df6": [
      16
    ],
    "531759bd": [
      16
    ],
    "5297c70b": [
      16
    ],
    "ffb6ce02": [
      16
    ],
    "135f9c09": [
      16
    ],
    "35c622ef": [
      15
    ],
    "ec44aeaa": [
      15
    ],
    "03586831": [
      15
    ],
    "55ccce36": [
      15
    ],
    "53c4d40c": [
      15
    ],
    "3718a044": [
      15
    ],
    "2fad2890": [
      15
    ],
    "0cf9aae6": [
      15
    ],
    "6209d2a2": [
      15
    ],
    "4a348b3d": [
      15
    ],
    "d1e2af74": [
      15
    ],
    "1b8d407b": [
      15
    ],
    "1540cf76": [
      15
    ],
    "39a95ee9": [
      15
    ],
    "02574418": [
      15
    ],
    "1e9641f0": [
      15
    ],
    "ef186964": [
      15
    ],
    "ded189c6": [
      15
    ],
    "2f79fc38": [
      15
    ],
    "142ea5ff": [
      15
    ],
    "48279e7e": [
      15
    ],
    "632501dd": [
      15
    ],
    "efd7889a": [
      15
    ],
    "fa6e7aac": [
      15
    ],
    "09e51ed6": [
      15
    ],
    "a1695b58": [
      15
    ],
    "5f088266": [
      15
    ],
    "12b1bed8": [
      15
    ],
    "8eace3e6": [
      15
    ],
    "00b7c840": [
      15
    ],
    "6c1730fa": [
      15
    ],
    "1170bd6f": [
      15
    ],
    "16ac8102": [
      15
    ],
    "2a67c63a": [
      15
    ],
    "0d457f14": [
      15
    ],
    "128510a2": [
      15
    ],
    "5d4d1fcc": [
      15
    ],
    "bc86535e": [
      15
    ],
    "2e063d91": [
      15
    ],
    "02e2dd29": [
      15
    ],
    "2a5d812b": [
      15
    ],
    "8098bade": [
      15
    ],
    "73ab762c": [
      15
    ],
    "2c088d56": [
      15
    ],
    "257fc1b5": [
      15
    ],
    "af43c85a": [
      15
    ],
    "a57daca0": [
      15
    ],
    "18d2cf55": [
      15
    ],
    "31979c5a": [
      15
    ],
    "68c4a31a": [
      15
    ],
    "30c4f4b8": [
      15
    ],
    "f817125c": [
      15
    ],
    "8ffc9f26": [
      15
    ],
    "775dfb46": [
      15
    ],
    "409cb9aa": [
      15
    ],
    "e6197542": [
      15
    ],
    "386a21aa": [
      15
    ],
    "3ae10d42": [
      15
    ],
    "5e603107": [
      15
    ],
    "5a860622": [
      15
    ],
    "1edb5593": [
      15
    ],
    "74890d16": [
      15
    ],
    "e03bf92a": [
      15
    ],
    "aaf49e08": [
      15
    ],
    "4b3b047c": [
      15
    ],
    "8529a06a": [
      15
    ],
    "50f94f6e": [
      15
    ],
    "20b3d24b": [
      15
    ],
    "0f524de0": [
      15
    ],
    "1579c017": [
      15
    ],
    "26c6aa62": [
      15
    ],
    "10c90fa2": [
      15
    ],
    "9e1189a2": [
      15
    ],
    "496c0feb": [
      15
    ],
    "6f895dab": [
      15
    ],
    "5fe55adf": [
      15
    ],
    "486874aa": [
      15
    ],
    "0285ee0d": [
      15
    ],
    "9d57846a": [
      15
    ],
    "174372af": [
      15
    ],
    "5076ba51": [
      15
    ],
    "f4233592": [
      15
    ],
    "c61560f0": [
      15
    ],
    "8f640446": [
      15
    ],
    "fe773628": [
      15
    ],
    "822aeb48": [
      15
    ],
    "6e2a128c": [
      15
    ],
    "467ad687": [
      15
    ],
    "a303560c": [
      15
    ],
    "25376c04": [
      15
    ],
    "6db66a26": [
      15
    ],
    "64796ff4": [
      15
    ],
    "bd28d486": [
      15
    ],
    "aba700b0": [
      15
    ],
    "00b45422": [
      15
    ],
    "9c688f36": [
      15
    ],
    "28cc160d": [
      15
    ],
    "798e9fe0": [
      15
    ],
    "8e618e2a": [
      15
    ],
    "f3f77d6c": [
      15
    ],
    "235dee66": [
      15
    ],
    "55f30ea8": [
      15
    ],
    "4ba0af15": [
      15
    ],
    "5eefed82": [
      15
    ],
    "e569e1e2": [
      15
    ],
    "d1a80064": [
      15
    ],
    "5fad90f8": [
      15
    ],
    "22bd49cf": [
      15
    ],
    "1cc1cd18": [
      15
    ],
    "11ce6cbf": [
      15
    ],
    "7160a8f2": [
      15
    ],
    "caf97122": [
      15
    ],
    "2efcc97f": [
      15
    ],
    "8ad27ade": [
      15
    ],
    "4e070048": [
      15
    ],
    "2c3f3c3b": [
      15
    ],
    "9c735f48": [
      15
    ],
    "29e6be42": [
      15
    ],
    "cb6ba4ea": [
      15
    ],
    "4283027c": [
      15
    ],
    "66be335c": [
      15
    ],
    "46ce3c56": [
      15
    ],
    "3f14f08a": [
      15
    ],
    "168edc7c": [
      15
    ],
    "9951d8ca": [
      15
    ],
    "5382a62d": [
      15
    ],
    "03fca794": [
      15
    ],
    "2c23fc72": [
      15
    ],
    "47c02640": [
      15
    ],
    "26a7b2e5": [
      15
    ],
    "5dc20e3a": [
      15
    ],
    "13ed2302": [
      15
    ],
    "1643cd3b": [
      15
    ],
    "b682537a": [
      15
    ],
    "71c0bac3": [
      15
    ],
    "de7f066e": [
      15
    ],
    "cb1192b8": [
      15
    ],
    "d356e2f8": [
      15
    ],
    "7129170b": [
      15
    ],
    "5ea62b42": [
      15
    ],
    "69ade132": [
      15
    ],
    "0c83b0fe": [
      15
    ],
    "0b8253e2": [
      15
    ],
    "425fa403": [
      15
    ],
    "71824bde": [
      15
    ],
    "e28f429c": [
      15
    ],
    "aed5d7fe": [
      15
    ],
    "8277c5dc": [
      15
    ],
    "7959b407": [
      15
    ],
    "129a7f06": [
      15
    ],
    "a949acea": [
      15
    ],
    "2bb8dc32": [
      15
    ],
    "54344e67": [
      15
    ],
    "a7e5028a": [
      15
    ],
    "4b2dd3c3": [
      15
    ],
    "591b83ba": [
      15
    ],
    "750d779a": [
      15
    ],
    "927de6ba": [
      15
    ],
    "3d3ba036": [
      15
    ],
    "575ada9a": [
      15
    ],
    "7525eb13": [
      15
    ],
    "487ab9fa": [
      15
    ],
    "10b75bd6": [
      15
    ],
    "713135db": [
      15
    ],
    "e0348d44": [
      15
    ],
    "19da735c": [
      15
    ],
    "0c6f29b0": [
      15
    ],
    "1b03ca94": [
      15
    ],
    "49b67d7e": [
      15
    ],
    "fa0536d2": [
      15
    ],
    "40029f27": [
      15
    ],
    "66b8f005": [
      15
    ],
    "90e76ba0": [
      15
    ],
    "347e35c4": [
      15
    ],
    "4b12e4a8": [
      15
    ],
    "6f334adb": [
      15
    ],
    "4af1b3f6": [
      15
    ],
    "d224bd44": [
      15
    ],
    "6f697560": [
      15
    ],
    "ecfba8c2": [
      15
    ],
    "b3fec8f6": [
      15
    ],
    "f8e424ea": [
      15
    ],
    "949d3876": [
      15
    ],
    "e0f7c110": [
      15
    ],
    "29ba184a": [
      15
    ],
    "f7f5aa88": [
      15
    ],
    "7636599c": [
      15
    ],
    "4f6b5812": [
      15
    ],
    "2d273c88": [
      15
    ],
    "1ee183d4": [
      15
    ],
    "edc846b8": [
      15
    ],
    "3108ad22": [
      15
    ],
    "58ce3aab": [
      15
    ],
    "284a530f": [
      15
    ],
    "7a549e02": [
      15
    ],
    "c86f365c": [
      15
    ],
    "3718c376": [
      15
    ],
    "3a8662d6": [
      15
    ],
    "010049ab": [
      15
    ],
    "20d08fa5": [
      15
    ],
    "2de6161b": [
      15
    ],
    "daa37762": [
      15
    ],
    "197f82a3": [
      15
    ],
    "4ac11734": [
      15
    ],
    "9c5a9a70": [
      15
    ],
    "c9529d9a": [
      15
    ],
    "60d3fe2b": [
      15
    ],
    "34c3f28b": [
      15
    ],
    "02e12476": [
      15
    ],
    "385a75df": [
      15
    ],
    "748d98f6": [
      15
    ],
    "73f0bbd6": [
      15
    ],
    "88ab2a1a": [
      15
    ],
    "d515e350": [
      15
    ],
    "78f4a97c": [
      15
    ],
    "0046913e": [
      15
    ],
    "17e3884c": [
      15
    ],
    "1c1a9592": [
      15
    ],
    "6a28e355": [
      15
    ],
    "64662f74": [
      15
    ],
    "ad306026": [
      15
    ],
    "1bb564aa": [
      15
    ],
    "60462c74": [
      15
    ],
    "183def84": [
      15
    ],
    "d250d5d8": [
      15
    ],
    "4dd13156": [
      15
    ],
    "76db940c": [
      15
    ],
    "f393b59a": [
      15
    ],
    "0cca68d4": [
      15
    ],
    "1fc8e0b0": [
      15
    ],
    "1084322b": [
      15
    ],
    "f38cb888": [
      15
    ],
    "79aba272": [
      15
    ],
    "062a7e7f": [
      15
    ],
    "1a816ed1": [
      15
    ],
    "6997f9fa": [
      15
    ],
    "17bd5dc0": [
      15
    ],
    "25cd4149": [
      15
    ],
    "10bcca92": [
      15
    ],
    "8d181044": [
      15
    ],
    "7af4f976": [
      15
    ],
    "1caf4102": [
      15
    ],
    "37dfe0d8": [
      15
    ],
    "52c1496a": [
      15
    ],
    "5b31c2a7": [
      15
    ],
    "477b0b28": [
      15
    ],
    "6adbc726": [
      15
    ],
    "90a8e568": [
      15
    ],
    "7f4e31b0": [
      15
    ],
    "4513c588": [
      15
    ],
    "97f56048": [
      15
    ],
    "7d5c720b": [
      15
    ],
    "577ff6bb": [
      16
    ],
    "3a41fb53": [
      16
    ],
    "6d130bcf": [
      16
    ],
    "568f6c8c": [
      16
    ],
    "07089d3e": [
      14
    ],
    "7b39d006": [
      14
    ],
    "4998ed3a": [
      14
    ],
    "7a2be430": [
      14
    ],
    "5927bace": [
      14
    ],
    "29f9f194": [
      14
    ],
    "7afd35ca": [
      14
    ],
    "44b26031": [
      14
    ],
    "5b125b8f": [
      14
    ],
    "3a4a77de": [
      14
    ],
    "199ae8f4": [
      14
    ],
    "e94e992a": [
      15
    ],
    "19dcca58": [
      15
    ],
    "4a2ae140": [
      15
    ],
    "1beeed4c": [
      11
    ],
    "5eff0e10": [
      11
    ],
    "5351a58c": [
      11
    ],
    "2af1106c": [
      2,
      9
    ],
    "43cc3a10": [
      9
    ],
    "45b1cec0": [
      1
    ],
    "2e4d0a16": [
      8
    ],
    "0dfcfdb2": [
      5
    ],
    "7e6a3a2f": [
      3
    ],
    "1ccbdd91": [
      4
    ],
    "e56733f4": [
      11
    ],
    "a0c24354": [
      11
    ],
    "5c2cbb90": [
      2,
      9
    ],
    "8a2952f0": [
      2,
      9
    ],
    "55cd4078": [
      9
    ],
    "78bd6fd8": [
      9
    ],
    "10cd1d8c": [
      1
    ],
    "7f9a0448": [
      1
    ],
    "38240fc1": [
      8
    ],
    "10b2cfde": [
      8
    ],
    "0d5ef666": [
      5
    ],
    "68e22816": [
      5
    ],
    "e1a0320a": [
      3
    ],
    "ae25e16a": [
      3
    ],
    "1c2dd645": [
      4
    ],
    "77b107f5": [
      4
    ],
    "259e10d5": [
      9
    ],
    "7896240e": [
      9
    ],
    "1cf4d8ac": [
      9
    ],
    "20e48aba": [
      9
    ],
    "65b19d3c": [
      9
    ],
    "690b8e8b": [
      11
    ],
    "75b31e35": [
      11
    ],
    "a6b13f32": [
      11
    ],
    "22cdb6fa": [
      2,
      9
    ],
    "9b710ffa": [
      2,
      9
    ],
    "6c4211b2": [
      2,
      9
    ],
    "4abd562d": [
      2,
      9
    ],
    "5971b346": [
      2,
      9
    ],
    "208ad908": [
      1
    ],
    "7a64cc13": [
      1
    ],
    "a8d64c36": [
      1
    ],
    "08a3d8ca": [
      1
    ],
    "674189a8": [
      8
    ],
    "2444c9b0": [
      8
    ],
    "c9923396": [
      8
    ],
    "68ae085c": [
      8
    ],
    "082d6aeb": [
      8
    ],
    "0d0c3043": [
      5
    ],
    "2916c83d": [
      5
    ],
    "6117eb46": [
      5
    ],
    "257f41d3": [
      5
    ],
    "919ead60": [
      5
    ],
    "247d2c9c": [
      3
    ],
    "d9f5a33a": [
      3
    ],
    "7163d276": [
      3
    ],
    "8fc117e6": [
      3
    ],
    "dfb0f50a": [
      3
    ],
    "fb44903c": [
      4
    ],
    "1827a79a": [
      4
    ],
    "cc9236f2": [
      4
    ],
    "1f56b46e": [
      4
    ],
    "2060bade": [
      4
    ]
  },
  "assetsMapping": {
    "3618f2e1": [
      "08299eb.modern.js"
    ],
    "67c13ec2": [
      "095152e.modern.js"
    ],
    "4d45c734": [
      "4cd3ef3.modern.js"
    ],
    "349edf93": [
      "51645e0.modern.js"
    ],
    "749c2580": [
      "564bc53.modern.js"
    ],
    "79980e3a": [
      "78091c1.modern.js"
    ],
    "6fca0322": [
      "7f52467.modern.js"
    ],
    "2a130dde": [
      "8f7831f.modern.js"
    ],
    "ed267066": [
      "9c18ccf.modern.js"
    ],
    "2aff1868": [
      "b567b5a.modern.js"
    ],
    "2cf24018": [
      "bef9e6b.modern.js"
    ],
    "122449dc": [
      "cc3b544.modern.js"
    ],
    "1a3ae26b": [
      "dc75398.modern.js"
    ],
    "7ea24c87": [
      "dc95ba1.modern.js"
    ],
    "085a35c4": [
      "e9b90e8.modern.js"
    ]
  }
}